LICENSE
MANIFEST.in
README.md
setup.py
gbwasdeqjp/__init__.py
gbwasdeqjp/api_helper.py
gbwasdeqjp/configuration.py
gbwasdeqjp/decorators.py
gbwasdeqjp/gbwasdeqjp_client.py
gbwasdeqjp.egg-info/PKG-INFO
gbwasdeqjp.egg-info/SOURCES.txt
gbwasdeqjp.egg-info/dependency_links.txt
gbwasdeqjp.egg-info/requires.txt
gbwasdeqjp.egg-info/top_level.txt
gbwasdeqjp/controllers/__init__.py
gbwasdeqjp/controllers/api_controller.py
gbwasdeqjp/controllers/base_controller.py
gbwasdeqjp/exceptions/__init__.py
gbwasdeqjp/exceptions/api_exception.py
gbwasdeqjp/http/__init__.py
gbwasdeqjp/http/http_call_back.py
gbwasdeqjp/http/http_client.py
gbwasdeqjp/http/http_context.py
gbwasdeqjp/http/http_method_enum.py
gbwasdeqjp/http/http_request.py
gbwasdeqjp/http/http_response.py
gbwasdeqjp/http/requests_client.py
gbwasdeqjp/http/auth/__init__.py
gbwasdeqjp/http/auth/basic_auth.py
gbwasdeqjp/models/__init__.py
gbwasdeqjp/models/suite_code_enum.py
tests/__init__.py
tests/http_response_catcher.py
tests/test_helper.py
tests/controllers/__init__.py
tests/controllers/controller_test_base.py
tests/controllers/test_api_controller.py